Metadata-Version: 1.1
Name: minimize-bibfile
Version: 0.0.1
Summary: Python package to identify and remove duplicated or near-duplicated bib entries.
Home-page: https://github.com/LucaCappelletti94/minimize_bibfile
Author: Luca Cappelletti
Author-email: cappelletti.luca94@gmail.com
License: MIT
Platform: UNKNOWN
Classifier: Development Status :: 3 - Alpha
Classifier: License :: OSI Approved :: MIT License
Classifier: Programming Language :: Python :: 3
